{
    "name": "Yammer",
    "owner": "WSO2",
    "category": "Federated authenticator",
    "documentationUrl": "https://docs.wso2.com/display/ISCONNECTORS/Yammer+Authenticator",
    "description": "The Yammer authenticator allows you to authenticate users using Yammer through the WSO2 Identity Server.",
    "status": "Active",
    "labels": ["SocialLogin"],
    "releases": [
        {
            "tagName": "1.0.0",
            "products": [
                "IS 6.0.0"
            ]
        }
    ]
}
